ethereum_types/__init__.py
ethereum_types/bytes.py
ethereum_types/frozen.py
ethereum_types/numeric.py
ethereum_types/py.typed
ethereum_types-0.2.4.dist-info/licenses/LICENSE.md
ethereum_types-0.2.4.dist-info/METADATA
ethereum_types-0.2.4.dist-info/WHEEL
ethereum_types-0.2.4.dist-info/top_level.txt
ethereum_types-0.2.4.dist-info/RECORD
